CODE_OF_CONDUCT.md
CONTRIBUTING.md
KEYBINDINGS.md
LICENSE.md
MANIFEST.in
README.md
setup.py
ash_editor.egg-info/PKG-INFO
ash_editor.egg-info/SOURCES.txt
ash_editor.egg-info/dependency_links.txt
ash_editor.egg-info/entry_points.txt
ash_editor.egg-info/requires.txt
ash_editor.egg-info/top_level.txt
assets/ash-default.png
assets/banner.png
assets/bmc-button.png
assets/ss1.png
assets/ss10.png
assets/ss11.png
assets/ss12.png
assets/ss13.png
assets/ss14.png
assets/ss15.png
assets/ss16.png
assets/ss17.png
assets/ss18.png
assets/ss19.png
assets/ss2.png
assets/ss20.png
assets/ss3.png
assets/ss4.png
assets/ss5.png
assets/ss6.png
assets/ss7.png
assets/ss8.png
assets/ss9.png
src/ash/__init__.py
src/ash/ash_main.py
src/ash/main.py
src/ash/core/__init__.py
src/ash/core/ashException.py
src/ash/core/bufferManager.py
src/ash/core/editHistory.py
src/ash/core/gitRepo.py
src/ash/core/internalClipboard.py
src/ash/core/logger.py
src/ash/core/screen.pyx
src/ash/core/sessionStorage.py
src/ash/formatting/__init__.py
src/ash/formatting/colors.py
src/ash/formatting/formatting.py
src/ash/formatting/syntaxHighlighting.py
src/ash/formatting/themeManager.py
src/ash/gui/__init__.py
src/ash/gui/checkbox.py
src/ash/gui/cursorPosition.py
src/ash/gui/dialogHandler.py
src/ash/gui/editor.py
src/ash/gui/editorKeyHandler.py
src/ash/gui/editorUtility.py
src/ash/gui/fileLoader.py
src/ash/gui/findReplaceDialog.py
src/ash/gui/groupedListbox.py
src/ash/gui/inputBox.py
src/ash/gui/label.py
src/ash/gui/listbox.py
src/ash/gui/menuBar.py
src/ash/gui/modalDialog.py
src/ash/gui/msgBox.py
src/ash/gui/popupMenu.py
src/ash/gui/projectFindReplaceDialog.py
src/ash/gui/statusbar.py
src/ash/gui/textfield.py
src/ash/gui/topLevelWindow.py
src/ash/gui/treeview.py
src/ash/gui/window.py
src/ash/gui/windowManager.py
src/ash/utils/__init__.py
src/ash/utils/commandUtils.py
src/ash/utils/fileUtils.py
src/ash/utils/keyMappingsManager.py
src/ash/utils/keyUtils.py
src/ash/utils/localisationManager.py
src/ash/utils/settingsManager.py
src/ash/utils/snippetManager.py
src/ash/utils/utils.py