Metadata-Version: 2.1
Name: ash-editor
Version: 0.1.0.dev14
Summary: A modern terminal text-editor
Home-page: https://akashnag.github.io/ash
Author: Akash Nag
Author-email: nag.akash.cs@gmail.com
License: MIT
Keywords: terminal text-editor
Platform: UNKNOWN
Classifier: License :: OSI Approved :: MIT License
Classifier: Programming Language :: Python :: 3.8
Classifier: Topic :: Text Editors
